recognizer/__init__.py
recognizer/alphabet.py
recognizer/data.py
recognizer/recognizer.py
recognizer/split.py
recognizer/symbol.py
recognizer/data/A.png
recognizer/data/B.png
recognizer/data/C.png
recognizer/data/D.png
recognizer/data/E.png
recognizer/data/F.png
recognizer/data/G.png
recognizer/data/H.png
recognizer/data/I.png
recognizer/data/J.png
recognizer/data/K.png
recognizer/data/L.png
recognizer/data/M.png
recognizer/data/N.png
recognizer/data/O.png
recognizer/data/P.png
recognizer/data/Q.png
recognizer/data/R.png
recognizer/data/S.png
recognizer/data/T.png
recognizer/data/U.png
recognizer/data/V.png
recognizer/data/W.png
recognizer/data/X.png
recognizer/data/Y.png
recognizer/data/Z.png
recognizer/data/a_.png
recognizer/data/b_.png
recognizer/data/c_.png
recognizer/data/d_.png
recognizer/data/e_.png
recognizer/data/f_.png
recognizer/data/g_.png
recognizer/data/h_.png
recognizer/data/i_.png
recognizer/data/j_.png
recognizer/data/k_.png
recognizer/data/l_.png
recognizer/data/m_.png
recognizer/data/n_.png
recognizer/data/o_.png
recognizer/data/p_.png
recognizer/data/q_.png
recognizer/data/r_.png
recognizer/data/s_.png
recognizer/data/t_.png
recognizer/data/u_.png
recognizer/data/v_.png
recognizer/data/w_.png
recognizer/data/x_.png
recognizer/data/y_.png
recognizer/data/z_.png
recognizer/methods/__init__.py
recognizer/methods/base.py
recognizer/methods/corr.py
recognizer/methods/morph.py
sym_recognizer-0.0.6.dist-info/LICENSE.md
sym_recognizer-0.0.6.dist-info/METADATA
sym_recognizer-0.0.6.dist-info/WHEEL
sym_recognizer-0.0.6.dist-info/top_level.txt
sym_recognizer-0.0.6.dist-info/RECORD
